pay_by_square.py
pay_by_square-0.2.0.dist-info/LICENSE
pay_by_square-0.2.0.dist-info/WHEEL
pay_by_square-0.2.0.dist-info/METADATA
pay_by_square-0.2.0.dist-info/RECORD
