Metadata-Version: 2.1
Name: pay-by-square
Version: 0.2.0
Summary: Generate QR codes for by square payments
Home-page: https://github.com/matusf/pay-by-square
License: MIT
Keywords: payments,qrcode,pay,by-square,pay-by-square
Author: Matúš Ferech
Requires-Python: >=3.6,<4.0
Classifier: License :: OSI Approved :: MIT License
Classifier: Programming Language :: Python :: 3
Classifier: Programming Language :: Python :: 3.6
Classifier: Programming Language :: Python :: 3.7
Classifier: Programming Language :: Python :: 3.8
Project-URL: Repository, https://github.com/matusf/pay-by-square
